sng_parser/__init__.py
sng_parser/database.py
sng_parser/parser.py
sng_parser/utils.py
sng_parser/_data/phrasal-preps.txt
sng_parser/_data/phrasal-verbs.txt
sng_parser/_data/scene-nouns.txt
sng_parser/backends/__init__.py
sng_parser/backends/backend.py
sng_parser/backends/spacy_parser.py
SceneGraphParser-0.1.0.dist-info/LICENSE
SceneGraphParser-0.1.0.dist-info/METADATA
SceneGraphParser-0.1.0.dist-info/WHEEL
SceneGraphParser-0.1.0.dist-info/top_level.txt
SceneGraphParser-0.1.0.dist-info/RECORD
