Metadata-Version: 2.1
Name: SceneGraphParser
Version: 0.1.0
Summary: A python toolkit for parsing sentences (natural language) into scene graphs (symbolic representations).
Home-page: 
Author: 
License: MIT
Keywords: nlp
Platform: UNKNOWN
Classifier: Development Status :: 3 - Alpha
Classifier: Intended Audience :: Science/Research
Classifier: License :: OSI Approved :: MIT License
Classifier: Programming Language :: Python :: 3.6
Classifier: Topic :: Text Processing
License-File: LICENSE
Requires-Dist: spacy (>=3.2.0)
Requires-Dist: tabulate (>=0.8.9)
